[
  {"id":1,"title":"Sunrise City","artist":"Neon Echo","genre":"pop","mood":"happy","energy":0.82,"tempo_bpm":118,"valence":0.84,"danceability":0.79,"acousticness":0.18},
  {"id":2,"title":"Midnight Coding","artist":"LoRoom","genre":"lofi","mood":"chill","energy":0.42,"tempo_bpm":78,"valence":0.56,"danceability":0.62,"acousticness":0.71},
  {"id":3,"title":"Storm Runner","artist":"Voltline","genre":"rock","mood":"intense","energy":0.91,"tempo_bpm":152,"valence":0.48,"danceability":0.66,"acousticness":0.10},
  {"id":4,"title":"Library Rain","artist":"Paper Lanterns","genre":"lofi","mood":"chill","energy":0.35,"tempo_bpm":72,"valence":0.60,"danceability":0.58,"acousticness":0.86},
  {"id":5,"title":"Gym Hero","artist":"Max Pulse","genre":"pop","mood":"intense","energy":0.93,"tempo_bpm":132,"valence":0.77,"danceability":0.88,"acousticness":0.05},
  {"id":6,"title":"Spacewalk Thoughts","artist":"Orbit Bloom","genre":"ambient","mood":"chill","energy":0.28,"tempo_bpm":60,"valence":0.65,"danceability":0.41,"acousticness":0.92},
  {"id":7,"title":"Coffee Shop Stories","artist":"Slow Stereo","genre":"jazz","mood":"relaxed","energy":0.37,"tempo_bpm":90,"valence":0.71,"danceability":0.54,"acousticness":0.89},
  {"id":8,"title":"Night Drive Loop","artist":"Neon Echo","genre":"synthwave","mood":"moody","energy":0.75,"tempo_bpm":110,"valence":0.49,"danceability":0.73,"acousticness":0.22},
  {"id":9,"title":"Focus Flow","artist":"LoRoom","genre":"lofi","mood":"focused","energy":0.40,"tempo_bpm":80,"valence":0.59,"danceability":0.60,"acousticness":0.78},
  {"id":10,"title":"Rooftop Lights","artist":"Indigo Parade","genre":"indie pop","mood":"happy","energy":0.76,"tempo_bpm":124,"valence":0.81,"danceability":0.82,"acousticness":0.35},
  {"id":11,"title":"Empty Porch","artist":"Willow Creek","genre":"folk","mood":"sad","energy":0.22,"tempo_bpm":68,"valence":0.18,"danceability":0.31,"acousticness":0.94},
  {"id":12,"title":"Neon Surge","artist":"Bass Circuit","genre":"edm","mood":"excited","energy":0.95,"tempo_bpm":140,"valence":0.88,"danceability":0.91,"acousticness":0.04},
  {"id":13,"title":"Iron Override","artist":"Fracture Point","genre":"metal","mood":"angry","energy":0.96,"tempo_bpm":168,"valence":0.22,"danceability":0.55,"acousticness":0.06},
  {"id":14,"title":"3AM Gravity","artist":"Velvet Shore","genre":"r&b","mood":"moody","energy":0.58,"tempo_bpm":88,"valence":0.38,"danceability":0.68,"acousticness":0.34},
  {"id":15,"title":"Morning Aria","artist":"The Still Quartet","genre":"classical","mood":"relaxed","energy":0.18,"tempo_bpm":58,"valence":0.72,"danceability":0.26,"acousticness":0.97},
  {"id":16,"title":"Golden Hour Bounce","artist":"Sunny Daze","genre":"hip-hop","mood":"happy","energy":0.78,"tempo_bpm":96,"valence":0.85,"danceability":0.84,"acousticness":0.12},
  {"id":17,"title":"Deep State Alpha","artist":"Theta Pulse","genre":"electronic","mood":"focused","energy":0.55,"tempo_bpm":92,"valence":0.52,"danceability":0.63,"acousticness":0.08},
  {"id":18,"title":"Rust Belt Hymn","artist":"Hollow Rail","genre":"blues","mood":"sad","energy":0.39,"tempo_bpm":66,"valence":0.28,"danceability":0.44,"acousticness":0.72},
  {"id":19,"title":"Hall of Fame","artist":"Stray Kids","genre":"k-pop","mood":"excited","energy":0.89,"tempo_bpm":133,"valence":0.72,"danceability":0.86,"acousticness":0.07},
  {"id":20,"title":"Heartbeat Drop","artist":"Neon Echo","genre":"pop","mood":"excited","energy":0.88,"tempo_bpm":128,"valence":0.82,"danceability":0.86,"acousticness":0.10},
  {"id":21,"title":"Summer Static","artist":"Indigo Parade","genre":"pop","mood":"happy","energy":0.84,"tempo_bpm":122,"valence":0.86,"danceability":0.83,"acousticness":0.15},
  {"id":22,"title":"Electric Feel","artist":"Sunny Daze","genre":"pop","mood":"excited","energy":0.91,"tempo_bpm":130,"valence":0.80,"danceability":0.88,"acousticness":0.08},
  {"id":23,"title":"Neon Idol","artist":"Stray Kids","genre":"k-pop","mood":"excited","energy":0.90,"tempo_bpm":136,"valence":0.75,"danceability":0.87,"acousticness":0.06},
  {"id":24,"title":"Cherry Blossom Wave","artist":"Orbit Bloom","genre":"k-pop","mood":"happy","energy":0.85,"tempo_bpm":128,"valence":0.83,"danceability":0.84,"acousticness":0.09},
  {"id":25,"title":"Pixel Dreams","artist":"Theta Pulse","genre":"k-pop","mood":"excited","energy":0.87,"tempo_bpm":134,"valence":0.78,"danceability":0.85,"acousticness":0.07},
  {"id":26,"title":"Rainy Window","artist":"LoRoom","genre":"lofi","mood":"chill","energy":0.38,"tempo_bpm":76,"valence":0.62,"danceability":0.56,"acousticness":0.82},
  {"id":27,"title":"Dusk Session","artist":"Paper Lanterns","genre":"lofi","mood":"focused","energy":0.43,"tempo_bpm":82,"valence":0.55,"danceability":0.61,"acousticness":0.79},
  {"id":28,"title":"Stellar Drift","artist":"Orbit Bloom","genre":"ambient","mood":"chill","energy":0.25,"tempo_bpm":62,"valence":0.68,"danceability":0.38,"acousticness":0.94},
  {"id":29,"title":"Cloud Architecture","artist":"Theta Pulse","genre":"ambient","mood":"relaxed","energy":0.30,"tempo_bpm":58,"valence":0.70,"danceability":0.42,"acousticness":0.91},
  {"id":30,"title":"Late Night Brew","artist":"Slow Stereo","genre":"jazz","mood":"relaxed","energy":0.40,"tempo_bpm":85,"valence":0.74,"danceability":0.52,"acousticness":0.88},
  {"id":31,"title":"Velvet Chords","artist":"Slow Stereo","genre":"jazz","mood":"moody","energy":0.45,"tempo_bpm":94,"valence":0.42,"danceability":0.58,"acousticness":0.85},
  {"id":32,"title":"Voltage Rush","artist":"Voltline","genre":"rock","mood":"intense","energy":0.89,"tempo_bpm":148,"valence":0.52,"danceability":0.68,"acousticness":0.12},
  {"id":33,"title":"Broken Glass Road","artist":"Hollow Rail","genre":"rock","mood":"moody","energy":0.72,"tempo_bpm":132,"valence":0.35,"danceability":0.62,"acousticness":0.18},
  {"id":34,"title":"Shatter Protocol","artist":"Fracture Point","genre":"metal","mood":"angry","energy":0.97,"tempo_bpm":172,"valence":0.18,"danceability":0.51,"acousticness":0.05},
  {"id":35,"title":"Bass Overload","artist":"Bass Circuit","genre":"edm","mood":"excited","energy":0.94,"tempo_bpm":142,"valence":0.85,"danceability":0.90,"acousticness":0.03},
  {"id":36,"title":"Midnight Rave","artist":"Theta Pulse","genre":"edm","mood":"intense","energy":0.92,"tempo_bpm":138,"valence":0.60,"danceability":0.88,"acousticness":0.04},
  {"id":37,"title":"Velvet Smoke","artist":"Velvet Shore","genre":"r&b","mood":"moody","energy":0.55,"tempo_bpm":84,"valence":0.42,"danceability":0.65,"acousticness":0.38},
  {"id":38,"title":"Golden Glow","artist":"Velvet Shore","genre":"r&b","mood":"happy","energy":0.68,"tempo_bpm":92,"valence":0.78,"danceability":0.72,"acousticness":0.28},
  {"id":39,"title":"Nocturne in Blue","artist":"The Still Quartet","genre":"classical","mood":"sad","energy":0.15,"tempo_bpm":56,"valence":0.28,"danceability":0.22,"acousticness":0.98},
  {"id":40,"title":"String Theory","artist":"The Still Quartet","genre":"classical","mood":"relaxed","energy":0.20,"tempo_bpm":62,"valence":0.75,"danceability":0.28,"acousticness":0.96},
  {"id":41,"title":"Block Party","artist":"Max Pulse","genre":"hip-hop","mood":"excited","energy":0.82,"tempo_bpm":98,"valence":0.88,"danceability":0.86,"acousticness":0.10},
  {"id":42,"title":"Corner Store Legend","artist":"Sunny Daze","genre":"hip-hop","mood":"happy","energy":0.74,"tempo_bpm":94,"valence":0.82,"danceability":0.80,"acousticness":0.16},
  {"id":43,"title":"Wildflower Trail","artist":"Willow Creek","genre":"folk","mood":"relaxed","energy":0.28,"tempo_bpm":72,"valence":0.72,"danceability":0.38,"acousticness":0.92},
  {"id":44,"title":"Porch Light","artist":"Willow Creek","genre":"folk","mood":"sad","energy":0.25,"tempo_bpm":66,"valence":0.22,"danceability":0.34,"acousticness":0.90},
  {"id":45,"title":"Delta Crawl","artist":"Hollow Rail","genre":"blues","mood":"sad","energy":0.42,"tempo_bpm":68,"valence":0.25,"danceability":0.46,"acousticness":0.76},
  {"id":46,"title":"Smokestack City","artist":"Hollow Rail","genre":"blues","mood":"moody","energy":0.48,"tempo_bpm":72,"valence":0.32,"danceability":0.50,"acousticness":0.70},
  {"id":47,"title":"Arcade Hearts","artist":"Neon Echo","genre":"indie pop","mood":"happy","energy":0.72,"tempo_bpm":120,"valence":0.84,"danceability":0.78,"acousticness":0.32},
  {"id":48,"title":"Glass Ceiling","artist":"Indigo Parade","genre":"indie pop","mood":"moody","energy":0.62,"tempo_bpm":108,"valence":0.38,"danceability":0.65,"acousticness":0.44},
  {"id":49,"title":"Chrome Highway","artist":"Bass Circuit","genre":"synthwave","mood":"intense","energy":0.80,"tempo_bpm":116,"valence":0.55,"danceability":0.75,"acousticness":0.18},
  {"id":50,"title":"Signal Lost","artist":"Theta Pulse","genre":"electronic","mood":"focused","energy":0.58,"tempo_bpm":96,"valence":0.48,"danceability":0.66,"acousticness":0.10}
]
